SpaGRA/__init__.py
SpaGRA/gat.py
SpaGRA/loss.py
SpaGRA/process.py
SpaGRA/train_model.py
SpaGRA/utils.py
SpaGRA-1.0.0.dist-info/LICENSE.txt
SpaGRA-1.0.0.dist-info/METADATA
SpaGRA-1.0.0.dist-info/WHEEL
SpaGRA-1.0.0.dist-info/top_level.txt
SpaGRA-1.0.0.dist-info/RECORD
