Metadata-Version: 2.1
Name: SpaGRA
Version: 1.0.0
Summary: Relation-aware graph augmentation with geometric contrastive learning improves the domains identification from spatially resolved transcriptomics data
Author: Sun Xue
Author-email: sunxue_yy@mail.edu.sdu.cn
License: MIT
Keywords: Spatial transcriptomics,Deep learning,Domains identification
License-File: LICENSE.txt
Requires-Dist: requests
